vault_psycopg2/__init__.py
vault_psycopg2/vault.py
vault_psycopg2-0.1.11.dist-info/LICENSE
vault_psycopg2-0.1.11.dist-info/METADATA
vault_psycopg2-0.1.11.dist-info/WHEEL
vault_psycopg2-0.1.11.dist-info/top_level.txt
vault_psycopg2-0.1.11.dist-info/RECORD
