Metadata-Version: 2.1
Name: vault-psycopg2
Version: 0.1.11
Summary: Helper classes to integrate psycopg2 with Vault
Home-page: https://github.com/niranjan94/vault-psycopg2
Author: Niranjan Rajendran (@niranjan94)
Author-email: me@niranjan.io
Maintainer: Niranjan Rajendran (@niranjan94)
Maintainer-email: me@niranjan.io
License: UNKNOWN
Platform: UNKNOWN
Classifier: Programming Language :: Python :: 3
Classifier: License :: OSI Approved :: MIT License
Classifier: Operating System :: OS Independent
Requires-Dist: hvac (>=0.3.0)
Requires-Dist: psycopg2-binary (>=2.0.0)
